polythlang/__init__.py
polythlang/ai_engine.py
polythlang/cli.py
polythlang/compiler.py
polythlang/core.py
polythlang/evaluator.py
polythlang/executor.py
polythlang/monitor.py
polythlang/optimization.py
polythlang/parser.py
polythlang/polyglot.py
polythlang/runtime.py
polythlang_mbc-1.0.2.dist-info/licenses/LICENSE
polythlang_mbc-1.0.2.dist-info/METADATA
polythlang_mbc-1.0.2.dist-info/WHEEL
polythlang_mbc-1.0.2.dist-info/entry_points.txt
polythlang_mbc-1.0.2.dist-info/top_level.txt
polythlang_mbc-1.0.2.dist-info/RECORD
