Metadata-Version: 2.4
Name: polythlang-mbc
Version: 1.0.2
Summary: The Polyglot AI Programming Language - Multi-paradigm language with AI engine, quantum computing, and semantic analysis
Home-page: https://github.com/MichaelCrowe11/polythlang
Author: Michael Benjamin Crowe
Author-email: Michael Benjamin Crowe <michael@crowelogic.com>
License: Apache-2.0
Project-URL: Homepage, https://github.com/MichaelCrowe11/polythlang
Project-URL: Documentation, https://github.com/MichaelCrowe11/polythlang
Project-URL: Repository, https://github.com/MichaelCrowe11/polythlang
Project-URL: Issues, https://github.com/MichaelCrowe11/polythlang/issues
Keywords: programming-language,polyglot,ai,quantum,compiler,multi-paradigm,python,javascript,rust
Classifier: Development Status :: 4 - Beta
Classifier: Intended Audience :: Developers
Classifier: Topic :: Software Development :: Libraries :: Python Modules
Classifier: Topic :: Scientific/Engineering :: Artificial Intelligence
Classifier: License :: OSI Approved :: Apache Software License
Classifier: Programming Language :: Python :: 3
Classifier: Programming Language :: Python :: 3.8
Classifier: Programming Language :: Python :: 3.9
Classifier: Programming Language :: Python :: 3.10
Classifier: Programming Language :: Python :: 3.11
Classifier: Programming Language :: Python :: 3.12
Classifier: Operating System :: OS Independent
Requires-Python: >=3.8
License-File: LICENSE
Requires-Dist: click>=8.0
Requires-Dist: pyyaml>=6.0
Requires-Dist: requests>=2.28
Requires-Dist: rich>=13.0
Requires-Dist: aiohttp>=3.8
Requires-Dist: pydantic>=2.0
Provides-Extra: dev
Requires-Dist: pytest>=7.0; extra == "dev"
Requires-Dist: pytest-asyncio>=0.21; extra == "dev"
Requires-Dist: black>=23.0; extra == "dev"
Requires-Dist: mypy>=1.0; extra == "dev"
Requires-Dist: ruff>=0.1.0; extra == "dev"
Provides-Extra: ide
Requires-Dist: flask>=2.3; extra == "ide"
Requires-Dist: flask-cors>=4.0; extra == "ide"
Requires-Dist: websockets>=11.0; extra == "ide"
Provides-Extra: monitoring
Requires-Dist: prometheus-client>=0.16; extra == "monitoring"
Requires-Dist: grafana-api>=1.0; extra == "monitoring"
Dynamic: author
Dynamic: home-page
Dynamic: license-file
Dynamic: requires-python
